flask_httpretty/__init__.py
flask_httpretty/core.py
Flask_httpretty-1.3.0.dist-info/DESCRIPTION.rst
Flask_httpretty-1.3.0.dist-info/METADATA
Flask_httpretty-1.3.0.dist-info/metadata.json
Flask_httpretty-1.3.0.dist-info/RECORD
Flask_httpretty-1.3.0.dist-info/top_level.txt
Flask_httpretty-1.3.0.dist-info/WHEEL
tests/__init__.py
tests/conftest.py
tests/test_mock_request.py
tests/test_multiple_app.py
