Metadata-Version: 2.0
Name: Flask-httpretty
Version: 1.3.0
Summary: flask-httpretty help you to mock http requests via flask.
Home-page: http://github.com/admire93/flask-httpretty
Author: Hyojun Kang
Author-email: hyojun@admire.kr
License: BSD
Platform: any
Classifier: Environment :: Web Environment
Classifier: Intended Audience :: Developers
Classifier: License :: OSI Approved :: BSD License
Classifier: Operating System :: OS Independent
Classifier: Programming Language :: Python
Classifier: Topic :: Internet :: WWW/HTTP :: Dynamic Content
Classifier: Topic :: Software Development :: Libraries :: Python Modules
Requires-Dist: Flask
Requires-Dist: httpretty
Provides-Extra: tests
Requires-Dist: pytest; extra == 'tests'
Requires-Dist: flake8; extra == 'tests'
